{
  "type": "OpenAPI30",
  "name": "USPTO Dataset API",
  "description": "Creates an API using the USPTO Data Set API (DSAPI) as a basis.",
  "document": "{\n    \"openapi\": \"3.0.1\",\n    \"info\": {\n        \"title\": \"USPTO Data Set API\",\n        \"description\": \"The Data Set API (DSAPI) allows the public users to discover and search USPTO exported data sets. This is a generic API that allows USPTO users to make any CSV based data files searchable through API. With the help of GET call, it returns the list of data fields that are searchable. With the help of POST call, data can be fetched based on the filters on the field names. Please note that POST call is used to search the actual data. The reason for the POST call is that it allows users to specify any complex search criteria without worry about the GET size limitations as well as encoding of the input parameters.\",\n        \"contact\": {\n            \"name\": \"Open Data Portal\",\n            \"url\": \"https://developer.uspto.gov\",\n            \"email\": \"developer@uspto.gov\"\n        },\n        \"version\": \"1.0.0\"\n    },\n    \"servers\": [\n        {\n            \"url\": \"{scheme}://developer.uspto.gov/ds-api\",\n            \"variables\": {\n                \"scheme\": {\n                    \"enum\": [\n                        \"https\",\n                        \"http\"\n                    ],\n                    \"default\": \"https\",\n                    \"description\": \"The Data Set API is accessible via https and http\"\n                }\n            }\n        }\n    ],\n    \"paths\": {\n        \"/\": {\n            \"get\": {\n                \"tags\": [\n                    \"metadata\"\n                ],\n                \"summary\": \"List available data sets\",\n                \"operationId\": \"list-data-sets\",\n                \"responses\": {\n                    \"200\": {\n                        \"description\": \"Returns a list of data sets\",\n                        \"content\": {\n                            \"application/json\": {\n                                \"schema\": {\n                                    \"$ref\": \"#/components/schemas/dataSetList\"\n                                },\n                                \"example\": {\n                                    \"total\": 2,\n                                    \"apis\": [\n                                        {\n                                            \"apiKey\": \"oa_citations\",\n                                            \"apiVersionNumber\": \"v1\",\n                                            \"apiUrl\": \"https://developer.uspto.gov/ds-api/oa_citations/v1/fields\",\n                                            \"apiDocumentationUrl\": \"https://developer.uspto.gov/ds-api-docs/index.html?url=https://developer.uspto.gov/ds-api/swagger/docs/oa_citations.json\"\n                                        },\n                                        {\n                                            \"apiKey\": \"cancer_moonshot\",\n                                            \"apiVersionNumber\": \"v1\",\n                                            \"apiUrl\": \"https://developer.uspto.gov/ds-api/cancer_moonshot/v1/fields\",\n                                            \"apiDocumentationUrl\": \"https://developer.uspto.gov/ds-api-docs/index.html?url=https://developer.uspto.gov/ds-api/swagger/docs/cancer_moonshot.json\"\n                                        }\n                                    ]\n                                }\n                            }\n                        }\n                    }\n                }\n            }\n        },\n        \"/{dataset}/{version}/fields\": {\n            \"get\": {\n                \"tags\": [\n                    \"metadata\"\n                ],\n                \"summary\": \"Provides the general information about the API and the list of fields that can be used to query the dataset.\",\n                \"description\": \"This GET API returns the list of all the searchable field names that are in the oa_citations. Please see the 'fields' attribute which returns an array of field names. Each field or a combination of fields can be searched using the syntax options shown below.\",\n                \"operationId\": \"list-searchable-fields\",\n                \"parameters\": [\n                    {\n                        \"name\": \"dataset\",\n                        \"in\": \"path\",\n                        \"description\": \"Name of the dataset.\",\n                        \"required\": true,\n                        \"schema\": {\n                            \"type\": \"string\"\n                        },\n                        \"example\": \"oa_citations\"\n                    },\n                    {\n                        \"name\": \"version\",\n                        \"in\": \"path\",\n                        \"description\": \"Version of the dataset.\",\n                        \"required\": true,\n                        \"schema\": {\n                            \"type\": \"string\"\n                        },\n                        \"example\": \"v1\"\n                    }\n                ],\n                \"responses\": {\n                    \"200\": {\n                        \"description\": \"The dataset API for the given version is found and it is accessible to consume.\",\n                        \"content\": {\n                            \"application/json\": {\n                                \"schema\": {\n                                    \"type\": \"string\"\n                                }\n                            }\n                        }\n                    },\n                    \"404\": {\n                        \"description\": \"The combination of dataset name and version is not found in the system or it is not published yet to be consumed by public.\",\n                        \"content\": {\n                            \"application/json\": {\n                                \"schema\": {\n                                    \"type\": \"string\"\n                                }\n                            }\n                        }\n                    }\n                }\n            }\n        },\n        \"/{dataset}/{version}/records\": {\n            \"post\": {\n                \"tags\": [\n                    \"search\"\n                ],\n                \"summary\": \"Provides search capability for the data set with the given search criteria.\",\n                \"description\": \"This API is based on Solr/Lucense Search. The data is indexed using SOLR. This GET API returns the list of all the searchable field names that are in the Solr Index. Please see the 'fields' attribute which returns an array of field names. Each field or a combination of fields can be searched using the Solr/Lucene Syntax. Please refer https://lucene.apache.org/core/3_6_2/queryparsersyntax.html#Overview for the query syntax. List of field names that are searchable can be determined using above GET api.\",\n                \"operationId\": \"perform-search\",\n                \"parameters\": [\n                    {\n                        \"name\": \"version\",\n                        \"in\": \"path\",\n                        \"description\": \"Version of the dataset.\",\n                        \"required\": true,\n                        \"schema\": {\n                            \"default\": \"v1\",\n                            \"type\": \"string\"\n                        }\n                    },\n                    {\n                        \"name\": \"dataset\",\n                        \"in\": \"path\",\n                        \"description\": \"Name of the dataset. In this case, the default value is oa_citations\",\n                        \"required\": true,\n                        \"schema\": {\n                            \"default\": \"oa_citations\",\n                            \"type\": \"string\"\n                        }\n                    }\n                ],\n                \"requestBody\": {\n                    \"content\": {\n                        \"application/x-www-form-urlencoded\": {\n                            \"schema\": {\n                                \"required\": [\n                                    \"criteria\"\n                                ],\n                                \"type\": \"object\",\n                                \"properties\": {\n                                    \"criteria\": {\n                                        \"description\": \"Uses Lucene Query Syntax in the format of propertyName:value, propertyName:[num1 TO num2] and date range format: propertyName:[yyyyMMdd TO yyyyMMdd]. In the response please see the 'docs' element which has the list of record objects. Each record structure would consist of all the fields and their corresponding values.\",\n                                        \"default\": \"*:*\",\n                                        \"type\": \"string\"\n                                    },\n                                    \"start\": {\n                                        \"description\": \"Starting record number. Default value is 0.\",\n                                        \"default\": 0,\n                                        \"type\": \"integer\"\n                                    },\n                                    \"rows\": {\n                                        \"description\": \"Specify number of rows to be returned. If you run the search with default values, in the response you will see 'numFound' attribute which will tell the number of records available in the dataset.\",\n                                        \"default\": 100,\n                                        \"type\": \"integer\"\n                                    }\n                                }\n                            }\n                        }\n                    }\n                },\n                \"responses\": {\n                    \"200\": {\n                        \"description\": \"successful operation\",\n                        \"content\": {\n                            \"application/json\": {\n                                \"schema\": {\n                                    \"type\": \"array\",\n                                    \"items\": {\n                                        \"type\": \"object\",\n                                        \"additionalProperties\": {\n                                            \"type\": \"object\"\n                                        }\n                                    }\n                                }\n                            }\n                        }\n                    },\n                    \"404\": {\n                        \"description\": \"No matching record found for the given criteria.\"\n                    }\n                }\n            }\n        }\n    },\n    \"components\": {\n        \"schemas\": {\n            \"dataSetList\": {\n                \"type\": \"object\",\n                \"properties\": {\n                    \"total\": {\n                        \"type\": \"integer\"\n                    },\n                    \"apis\": {\n                        \"type\": \"array\",\n                        \"items\": {\n                            \"type\": \"object\",\n                            \"properties\": {\n                                \"apiKey\": {\n                                    \"description\": \"To be used as a dataset parameter value\",\n                                    \"type\": \"string\"\n                                },\n                                \"apiVersionNumber\": {\n                                    \"description\": \"To be used as a version parameter value\",\n                                    \"type\": \"string\"\n                                },\n                                \"apiUrl\": {\n                                    \"format\": \"uriref\",\n                                    \"description\": \"The URL describing the dataset's fields\",\n                                    \"type\": \"string\"\n                                },\n                                \"apiDocumentationUrl\": {\n                                    \"format\": \"uriref\",\n                                    \"description\": \"A URL to the API console for each API\",\n                                    \"type\": \"string\"\n                                }\n                            }\n                        }\n                    }\n                }\n            }\n        }\n    },\n    \"tags\": [\n        {\n            \"name\": \"metadata\",\n            \"description\": \"Find out about the data sets\"\n        },\n        {\n            \"name\": \"search\",\n            \"description\": \"Search a data set\"\n        }\n    ]\n}"
}